{
  "settings": {
    "migrated": 6,
    "iconPacksPath": ".obsidian/icons",
    "fontSize": 16,
    "emojiStyle": "native",
    "iconColor": null,
    "recentlyUsedIcons": [
      "LiSettings",
      "🐍",
      "LiArchive",
      "LiClipboard",
      "LiFolder"
    ],
    "recentlyUsedIconsSize": 5,
    "rules": [],
    "extraMargin": {
      "top": 0,
      "right": 4,
      "bottom": 0,
      "left": 0
    },
    "iconInTabsEnabled": false,
    "iconInTitleEnabled": false,
    "iconInTitlePosition": "above",
    "iconInFrontmatterEnabled": false,
    "iconInFrontmatterFieldName": "icon",
    "iconColorInFrontmatterFieldName": "iconColor",
    "iconsBackgroundCheckEnabled": false,
    "iconsInNotesEnabled": true,
    "iconsInLinksEnabled": true,
    "iconIdentifier": ":",
    "lucideIconPackType": "native",
    "debugMode": false
  },
  "Python Deep Dive - 1 (Functional)": "LiFolder",
  "Python Deep Dive - 2 (Iterators, Generators)": "LiFolder",
  "Python Deep Dive - 3 (Dictionaries, Sets, JSON)": "LiFolder",
  "Python Deep Dive - 4 (OOP)": "LiFolder",
  "Python Deep Dive - 1 (Functional)/1.0.Quick Refresher.md": "LiArchive",
  "Python Deep Dive - 1 (Functional)/1.2.Multi-Line Statements And Strings.md": "LiClipboard",
  "Python Deep Dive - 1 (Functional)/1.3.Variable Names.md": "LiClipboard",
  "Python Deep Dive - 1 (Functional)/1.4.Conditionals.md": "LiClipboard",
  "Python Deep Dive - 1 (Functional)/1.5.Functions.md": "LiClipboard",
  "Python Deep Dive - 1 (Functional)/1.7.Classes.md": "LiClipboard",
  "Python Deep Dive - 1 (Functional)/0.Python Deep Dive 1.md": "🐍",
  "Python Deep Dive - 2 (Iterators, Generators)/0.Python Deep Dive 2.md": "🐍",
  "Python Deep Dive - 3 (Dictionaries, Sets, JSON)/0.Python Deep Dive 3.md": "🐍",
  "Python Deep Dive - 4 (OOP)/0.Python Deep Dive 4.md": "🐍",
  "README.md": "LiClipboard",
  "Python Deep Dive - 1 (Functional)/1.6.Loops.md": "LiClipboard",
  "Python Deep Dive - 1 (Functional)/2.1.Memory References.md": "LiClipboard",
  "Python Deep Dive - 1 (Functional)/2.0.Variables and Memory.md": "LiArchive",
  "Python Deep Dive - 1 (Functional)/1.1.Python Type Hierarchy.md": "LiClipboard",
  "Python Deep Dive - 1 (Functional)/2.2.Reference Counting.md": "LiClipboard",
  "Python Deep Dive - 1 (Functional)/2.3.Garbage Collection.md": "LiClipboard",
  "Python Deep Dive - 1 (Functional)/2.4.Dynamic vs Static typing.md": "LiClipboard",
  "Python Deep Dive - 1 (Functional)/2.5.Variable Re-Assignment.md": "LiClipboard",
  "Python Deep Dive - 1 (Functional)/2.6.Object Mutability.md": "LiClipboard",
  "Python Deep Dive - 1 (Functional)/2.7.Function Arguments And Mutability.md": "LiClipboard",
  "Python Deep Dive - 1 (Functional)/2.8.Shared References And Mutability.md": "LiClipboard",
  "Python Deep Dive - 1 (Functional)/2.9.Variable Equality.md": "LiClipboard",
  "Python Deep Dive - 1 (Functional)/2.10.Everything is an Object.md": "LiClipboard",
  "Python Deep Dive - 1 (Functional)/2.11.Python Optimizations - Interning.md": "LiClipboard",
  "Python Deep Dive - 1 (Functional)/2.12.Python Optimizations - String Interning.md": "LiClipboard",
  "Python Deep Dive - 1 (Functional)/2.13.Python Optimizations - PeepHoles.md": "LiClipboard",
  "Python Deep Dive - 1 (Functional)/3.0.Numeric Types.md": "LiArchive",
  "Python Deep Dive - 1 (Functional)/3.1.0.Integers Numbers.md": "LiClipboard",
  "Python Deep Dive - 1 (Functional)/3.1.1.Integers Operations.md": "LiClipboard",
  "Python Deep Dive - 1 (Functional)/3.1.2.Integers Constructors and Bases.md": "LiClipboard",
  "Python Deep Dive - 1 (Functional)/3.2.0.Rational Numbers.md": "LiClipboard",
  "Python Deep Dive - 1 (Functional)/3.3.1.Floats Equality Testing.md": "LiClipboard",
  "Python Deep Dive - 1 (Functional)/3.3.2.Floats Coercing to Integers.md": "LiClipboard",
  "Python Deep Dive - 1 (Functional)/3.3.3.Floats Rounding.md": "LiClipboard",
  "Python Deep Dive - 1 (Functional)/3.3.4.Decimals.md": "LiClipboard",
  "Python Deep Dive - 1 (Functional)/3.3.5.Decimals Constructors and Contexts.md": "LiClipboard",
  "Python Deep Dive - 1 (Functional)/3.3.6.Decimals Math Operations.md": "LiClipboard",
  "Python Deep Dive - 1 (Functional)/3.3.7.Decimals Performance Considerations.md": "LiClipboard",
  "Python Deep Dive - 1 (Functional)/3.4.0.Complex Numbers.md": "LiClipboard",
  "Python Deep Dive - 1 (Functional)/3.5.0.Booleans.md": "LiClipboard",
  "Python Deep Dive - 1 (Functional)/3.5.1.Booleans - Truth Values.md": "LiClipboard",
  "Python Deep Dive - 1 (Functional)/3.5.2.Booleans - Precedence and Short-Circuiting.md": "LiClipboard",
  "Python Deep Dive - 1 (Functional)/3.5.3.Booleans - Boolean Operators.md": "LiClipboard",
  "Python Deep Dive - 1 (Functional)/3.5.4.Booleans - Comparison Operators.md": "LiClipboard",
  "Python Deep Dive - 1 (Functional)/3.3.0.Real Numbers, Floats Internal Representation.md": "LiClipboard",
  "Assets": "LiSettings",
  "Python Deep Dive - 1 (Functional)/4.0.Functions.md": "LiArchive",
  "Python Deep Dive - 1 (Functional)/5.0.Decorators.md": "LiArchive",
  "Python Deep Dive - 1 (Functional)/7.0.Modules, Packages and Namespaces.md": "LiArchive",
  "Python Deep Dive - 1 (Functional)/4.1.0.Arguments vs Parameters.md": "LiClipboard",
  "Python Deep Dive - 1 (Functional)/4.1.1.Positional and Keyword Arguments.md": "LiClipboard",
  "Python Deep Dive - 1 (Functional)/4.2.0.Unpacking Iterables.md": "LiClipboard",
  "Python Deep Dive - 1 (Functional)/4.2.1.Extended Unpacking.md": "LiClipboard",
  "Python Deep Dive - 1 (Functional)/4.3.0.Args.md": "LiClipboard",
  "Python Deep Dive - 1 (Functional)/4.3.1.Keyword Arguments.md": "LiClipboard",
  "Python Deep Dive - 1 (Functional)/4.3.2.Kwargs.md": "LiClipboard",
  "Python Deep Dive - 1 (Functional)/4.3.4.Put It All Together.md": "LiClipboard",
  "Python Deep Dive - 1 (Functional)/4.4.0.Application - A Simple Function Timer.md": "LiClipboard",
  "Python Deep Dive - 1 (Functional)/4.5.0.Parameter Defaults.md": "LiClipboard",
  "Python Deep Dive - 1 (Functional)/4.6.0.Docstrings and Annotations.md": "LiClipboard",
  "Python Deep Dive - 1 (Functional)/4.7.0.Lambda Expressions.md": "LiClipboard",
  "Python Deep Dive - 1 (Functional)/4.7.1.Lambdas and Sorting.md": "LiClipboard",
  "Python Deep Dive - 1 (Functional)/4.8.0.Challenge - Randomize an Iterable using Sorted!.md": "LiClipboard",
  "Python Deep Dive - 1 (Functional)/4.9.0.Function Introspection.md": "LiClipboard",
  "Python Deep Dive - 1 (Functional)/4.10.0.Callables.md": "LiClipboard",
  "Python Deep Dive - 1 (Functional)/4.11.0.Map, Filter, Zip and List Comprehensions.md": "LiClipboard",
  "Python Deep Dive - 1 (Functional)/4.12.0.Reducing Functions.md": "LiClipboard",
  "Python Deep Dive - 1 (Functional)/4.13.0.The Operator Module.md": "LiClipboard",
  "Python Deep Dive - 1 (Functional)/5.1.0.Global and Local Scopes.md": "LiClipboard",
  "Python Deep Dive - 1 (Functional)/5.1.1.NonLocal Scopes.md": "LiClipboard",
  "Python Deep Dive - 1 (Functional)/5.2.0.Closures.md": "LiClipboard",
  "Python Deep Dive - 1 (Functional)/5.2.1.Closures - Application - Part 1.md": "LiClipboard",
  "Python Deep Dive - 1 (Functional)/5.2.2.Closures - Application - Part 2.md": "LiClipboard",
  "Python Deep Dive - 1 (Functional)/5.4.0.Decorator Application - Timer.md": "LiClipboard",
  "Python Deep Dive - 1 (Functional)/5.4.1.Decorator Application - Logger, Stacked Decorators.md": "LiClipboard",
  "Python Deep Dive - 1 (Functional)/5.4.2.Decorator Application - Memoization.md": "LiClipboard",
  "Python Deep Dive - 1 (Functional)/5.4.3.Decorator Application - Decorator Class.md": "LiClipboard",
  "Python Deep Dive - 1 (Functional)/5.4.4.Decorator Application - Decorating Classes.md": "LiClipboard",
  "Python Deep Dive - 1 (Functional)/5.4.5.Decorator Application - Dispatching - Part 1.md": "LiClipboard",
  "Python Deep Dive - 1 (Functional)/5.4.6.Decorator Application - Dispatching - Part 2.md": "LiClipboard",
  "Python Deep Dive - 1 (Functional)/5.4.7.Decorator Application - Dispatching - Part 3.md": "LiClipboard",
  "Python Deep Dive - 1 (Functional)/5.3.0.Decorators - Part 1.md": "LiClipboard",
  "Python Deep Dive - 1 (Functional)/6.1.0.Tuples as Data Structures.md": "LiClipboard",
  "Python Deep Dive - 1 (Functional)/6.0.Tuples.md": "LiArchive",
  "Python Deep Dive - 1 (Functional)/6.2.0.Named Tuples.md": "LiClipboard",
  "Python Deep Dive - 1 (Functional)/6.2.1.Named Tuples - Modifying and Extending.md": "LiClipboard",
  "Python Deep Dive - 1 (Functional)/6.2.2.Named Tuples - DocStrings and Default Values.md": "LiClipboard",
  "Python Deep Dive - 1 (Functional)/6.2.3.Named Tuples - Application.md": "LiClipboard",
  "Python Deep Dive - 1 (Functional)/8.0.Extras.md": "LiArchive",
  "Python Deep Dive - 1 (Functional)/7.1.0.What is a Module?.md": "LiClipboard",
  "Python Deep Dive - 1 (Functional)/7.2.0.How does Python Import Modules.md": "LiClipboard",
  "Python Deep Dive - 1 (Functional)/7.2.1.Imports and ImportLib.md": "LiClipboard",
  "Python Deep Dive - 1 (Functional)/7.2.2.Import Variants and Misconceptions.md": "LiClipboard",
  "Python Deep Dive - 1 (Functional)/7.3.0.Reloading Modules.md": "LiClipboard",
  "Python Deep Dive - 1 (Functional)/7.4.0.__main__.md": "LiClipboard",
  "Python Deep Dive - 1 (Functional)/7.5.0.Modules Recap.md": "LiClipboard",
  "Python Deep Dive - 1 (Functional)/7.6.0.What is a Package?.md": "LiClipboard",
  "Python Deep Dive - 1 (Functional)/7.6.1.Why Packages?.md": "LiClipboard",
  "Python Deep Dive - 1 (Functional)/7.6.2.Structuring Packages - Part 1.md": "LiClipboard",
  "Python Deep Dive - 1 (Functional)/7.6.3.Structuring Packages - Part 2.md": "LiClipboard",
  "Python Deep Dive - 1 (Functional)/7.7.0.Namespace Packages.md": "LiClipboard",
  "Python Deep Dive - 1 (Functional)/7.8.0.Importing from Zip Archives.md": "LiClipboard",
  "Python Deep Dive - 1 (Functional)/8.1.0.Python 3.10.md": "LiClipboard",
  "Python Deep Dive - 1 (Functional)/8.2.0.Python 3.9.md": "LiClipboard",
  "Python Deep Dive - 1 (Functional)/8.3.0.Python 3.8.md": "LiClipboard",
  "Python Deep Dive - 1 (Functional)/8.4.0.Python 3.6.md": "LiClipboard",
  "Python Deep Dive - 1 (Functional)/8.4.1.Python 3.6 - Dictionary Ordering.md": "LiClipboard",
  "Python Deep Dive - 1 (Functional)/8.4.2.Python 3.6 - Underscores in Numeric Literals.md": "LiClipboard",
  "Python Deep Dive - 1 (Functional)/8.4.4.Python 3.6 - f-Strings.md": "LiClipboard",
  "Python Deep Dive - 1 (Functional)/8.5.0.Additional Resources.md": "LiClipboard",
  "Python Deep Dive - 1 (Functional)/8.6.0.Random Seeds.md": "LiClipboard",
  "Python Deep Dive - 1 (Functional)/8.6.1.Random Choices.md": "LiClipboard",
  "Python Deep Dive - 1 (Functional)/8.6.2.Random Samples.md": "LiClipboard",
  "Python Deep Dive - 1 (Functional)/8.7.0.Timing Code using timeit.md": "LiClipboard",
  "Python Deep Dive - 1 (Functional)/8.8.0.Don't Use args and kwargs Blindly.md": "LiClipboard",
  "Python Deep Dive - 1 (Functional)/8.9.0.Command Line Arguments.md": "LiClipboard",
  "Python Deep Dive - 1 (Functional)/8.10.0.Sentniel Values for Parameter Default.md": "LiClipboard",
  "Python Deep Dive - 1 (Functional)/8.11.0.Simulating a Simple Switch in Python.md": "LiClipboard",
  "Python Deep Dive - 1 (Functional)/8.4.3.Python 3.6 - Preserved Order of kwargs & Named Tuple Application.md": "LiClipboard"
}